<annotation><folder>VOC2012</folder><filename>37286211405_4ebf0f4146_o.jpg</filename><source><database>The VOC2007 Database</database><annotation>PASCAL VOC2007</annotation><image>flickr</image></source><size><width>1920</width><height>960</height><depth>3</depth></size><segmented>0</segmented><object><name>person</name><pose>Unspecified</pose><truncated>0</truncated><difficult>0</difficult><bndbox><xmin>41</xmin><ymin>729</ymin><xmax>93</xmax><ymax>853</ymax></bndbox></object><object><name>person</name><pose>Unspecified</pose><truncated>0</truncated><difficult>0</difficult><bndbox><xmin>431</xmin><ymin>571</ymin><xmax>479</xmax><ymax>619</ymax></bndbox></object><object><name>person</name><pose>Unspecified</pose><truncated>0</truncated><difficult>0</difficult><bndbox><xmin>740</xmin><ymin>667</ymin><xmax>772</xmax><ymax>707</ymax></bndbox></object><object><name>person</name><pose>Unspecified</pose><truncated>0</truncated><difficult>0</difficult><bndbox><xmin>645</xmin><ymin>568</ymin><xmax>665</xmax><ymax>588</ymax></bndbox></object><object><name>person</name><pose>Unspecified</pose><truncated>0</truncated><difficult>0</difficult><bndbox><xmin>696</xmin><ymin>534</ymin><xmax>704</xmax><ymax>554</ymax></bndbox></object><object><name>person</name><pose>Unspecified</pose><truncated>0</truncated><difficult>0</difficult><bndbox><xmin>833</xmin><ymin>642</ymin><xmax>841</xmax><ymax>666</ymax></bndbox></object><object><name>person</name><pose>Unspecified</pose><truncated>0</truncated><difficult>0</difficult><bndbox><xmin>965</xmin><ymin>666</ymin><xmax>977</xmax><ymax>698</ymax></bndbox></object><object><name>person</name><pose>Unspecified</pose><truncated>0</truncated><difficult>0</difficult><bndbox><xmin>1099</xmin><ymin>649</ymin><xmax>1123</xmax><ymax>701</ymax></bndbox></object><object><name>person</name><pose>Unspecified</pose><truncated>0</truncated><difficult>0</difficult><bndbox><xmin>1204</xmin><ymin>643</ymin><xmax>1220</xmax><ymax>691</ymax></bndbox></object><object><name>person</name><pose>Unspecified</pose><truncated>0</truncated><difficult>0</difficult><bndbox><xmin>1293</xmin><ymin>638</ymin><xmax>1309</xmax><ymax>674</ymax></bndbox></object><object><name>person</name><pose>Unspecified</pose><truncated>0</truncated><difficult>0</difficult><bndbox><xmin>1326</xmin><ymin>621</ymin><xmax>1346</xmax><ymax>661</ymax></bndbox></object><object><name>person</name><pose>Unspecified</pose><truncated>0</truncated><difficult>0</difficult><bndbox><xmin>1473</xmin><ymin>602</ymin><xmax>1509</xmax><ymax>658</ymax></bndbox></object><object><name>person</name><pose>Unspecified</pose><truncated>0</truncated><difficult>0</difficult><bndbox><xmin>1541</xmin><ymin>540</ymin><xmax>1557</xmax><ymax>568</ymax></bndbox></object><object><name>person</name><pose>Unspecified</pose><truncated>0</truncated><difficult>0</difficult><bndbox><xmin>1663</xmin><ymin>535</ymin><xmax>1687</xmax><ymax>599</ymax></bndbox></object></annotation>